README.txt
setup.cfg
setup.py
docs/HISTORY.txt
docs/INSTALL.txt
docs/LICENSE.GPL
docs/LICENSE.txt
gomobile/__init__.py
gomobile.templates.egg-info/PKG-INFO
gomobile.templates.egg-info/SOURCES.txt
gomobile.templates.egg-info/dependency_links.txt
gomobile.templates.egg-info/entry_points.txt
gomobile.templates.egg-info/namespace_packages.txt
gomobile.templates.egg-info/not-zip-safe
gomobile.templates.egg-info/paster_plugins.txt
gomobile.templates.egg-info/requires.txt
gomobile.templates.egg-info/top_level.txt
gomobile/templates/__init__.py
gomobile/templates/theme.py
gomobile/templates/templates/gomobile_theme/setup.py_tmpl
gomobile/templates/templates/gomobile_theme/+namespace_package+/+package+/__init__.py
gomobile/templates/templates/gomobile_theme/+namespace_package+/+package+/configure.zcml_tmpl
gomobile/templates/templates/gomobile_theme/+namespace_package+/+package+/interfaces.py
gomobile/templates/templates/gomobile_theme/+namespace_package+/+package+/tests.py_tmpl
gomobile/templates/templates/gomobile_theme/+namespace_package+/+package+/viewlets.py_tmpl
gomobile/templates/templates/gomobile_theme/+namespace_package+/+package+/profiles/default/metadata.xml_tmpl
gomobile/templates/templates/gomobile_theme/+namespace_package+/+package+/profiles/default/propertiestool.xml_tmpl
gomobile/templates/templates/gomobile_theme/+namespace_package+/+package+/profiles/default/skins.xml_tmpl
gomobile/templates/templates/gomobile_theme/+namespace_package+/+package+/skins/+namespace_package+_+package+/skins_folder_readme.txt
gomobile/templates/templates/gomobile_theme/+namespace_package+/+package+/static/common.css_tmpl
gomobile/templates/templates/gomobile_theme/+namespace_package+/+package+/static/highend.css_tmpl
gomobile/templates/templates/gomobile_theme/+namespace_package+/+package+/static/logo.png
gomobile/templates/templates/gomobile_theme/+namespace_package+/+package+/static/lowend.css_tmpl
gomobile/templates/templates/gomobile_theme/+namespace_package+/+package+/static/theme.js_tmpl
gomobile/templates/templates/gomobile_theme/+namespace_package+/+package+/templates/additionalhead.pt
gomobile/templates/templates/gomobile_theme/docs/LICENSE.GPL
gomobile/templates/templates/gomobile_theme/docs/LICENSE.txt_tmpl