Metadata-Version: 1.0
Name: gomobile.templates
Version: 1.0
Summary: Project templates creating Web and Mobile themes for Plone
Home-page: http://webandmobile.mfabrik.com
Author: UNKNOWN
Author-email: UNKNOWN
License: GPL
Platform: UNKNOWN
Classifier: Framework :: Plone
Classifier: Programming Language :: Python
